sack/__init__.py
sack/assets.py
sack/components.py
sack/dev.py
sack/keybindings.py
sack/main.py
sack/screens.py
sack/styles.css
sack/util.py
sack/models/__init__.py
sack/models/client.py
sack/models/protocol.py
sack/models/server.py
sack_chat-1.1.0.dist-info/METADATA
sack_chat-1.1.0.dist-info/WHEEL
sack_chat-1.1.0.dist-info/entry_points.txt
sack_chat-1.1.0.dist-info/licenses/LICENSE
sack_chat-1.1.0.dist-info/RECORD
