Metadata-Version: 2.4
Name: sack-chat
Version: 1.1.0
Summary: Lightweight chat application for terminal
Project-URL: Repository, https://github.com/mati-33/sack
Author-email: mati <mateusz.meksula@gmail.com>
License-File: LICENSE
Keywords: chat,socket,tui
Classifier: Development Status :: 5 - Production/Stable
Classifier: Environment :: Console
Classifier: License :: OSI Approved :: MIT License
Classifier: Programming Language :: Python :: 3
Classifier: Topic :: Communications :: Chat
Requires-Python: >=3.10
Requires-Dist: textual>=3.5.0
